{
  "id": "671d5578-2449-4e62-9e57-710af5c3f242",
  "createdAt": "2025-08-13T19:38:25.578Z",
  "form": {
    "destination": "Paris",
    "startDate": "2025-08-13",
    "endDate": "2025-08-16",
    "travelers": 2,
    "currency": "EUR",
    "budget": 1200,
    "pace": "balanced",
    "interests": [
      "culture",
      "food"
    ],
    "mustSee": [],
    "tone": "Concise",
    "detail": "Concise",
    "activitiesPerDay": 3,
    "includeFlights": false
  },
  "itinerary": [
    {
      "day": 1,
      "title": "Day 1 • Paris",
      "activities": [
        {
          "timeOfDay": "morning",
          "name": "Morning walking tour",
          "note": "Buy skip-the-line if possible."
        },
        {
          "timeOfDay": "afternoon",
          "name": "Local market tasting"
        },
        {
          "timeOfDay": "evening",
          "name": "Iconic landmark visit"
        }
      ]
    },
    {
      "day": 2,
      "title": "Day 2 • Paris",
      "activities": [
        {
          "timeOfDay": "morning",
          "name": "Museum or gallery",
          "note": "Buy skip-the-line if possible."
        },
        {
          "timeOfDay": "afternoon",
          "name": "Scenic viewpoint"
        },
        {
          "timeOfDay": "evening",
          "name": "Neighborhood stroll"
        }
      ]
    },
    {
      "day": 3,
      "title": "Day 3 • Paris",
      "activities": [
        {
          "timeOfDay": "morning",
          "name": "Riverfront / seaside time",
          "note": "Buy skip-the-line if possible."
        },
        {
          "timeOfDay": "afternoon",
          "name": "Dinner at a cozy spot"
        },
        {
          "timeOfDay": "evening",
          "name": "Street-food crawl"
        }
      ]
    },
    {
      "day": 4,
      "title": "Day 4 • Paris",
      "activities": [
        {
          "timeOfDay": "morning",
          "name": "Morning walking tour",
          "note": "Buy skip-the-line if possible."
        },
        {
          "timeOfDay": "afternoon",
          "name": "Local market tasting"
        },
        {
          "timeOfDay": "evening",
          "name": "Iconic landmark visit"
        }
      ]
    }
  ]
}